{
    "name": "Tags",
    "fields": [
        {
            "fieldName": "descripcion",
            "fieldType": "String"
        }
    ],
    "relationships": [
        {
            "relationshipType": "many-to-many",
            "otherEntityName": "sugerenciaProducto",
            "otherEntityRelationshipName": "tags",
            "relationshipName": "sugerenciaProducto",
            "otherEntityField": "id",
            "ownerSide": false
        }
    ],
    "changelogDate": "20190706184356",
    "entityTableName": "tags",
    "dto": "no",
    "pagination": "no",
    "service": "no",
    "jpaMetamodelFiltering": false,
    "fluentMethods": true,
    "clientRootFolder": "",
    "applications": "*"
}